shape_registration/__init__.py
shape_registration/cropping.py
shape_registration/delaunay.py
shape_registration/entrypoints.py
shape_registration/lightning_registration.py
shape_registration/losses.py
shape_registration/procrustes.py
shape_registration/register.py
shape_registration/regularizer.py
shape_registration/sampling.py
shape_registration/transformation.py
shape_registration/utils.py
shape_registration-0.1.0.dist-info/METADATA
shape_registration-0.1.0.dist-info/WHEEL
shape_registration-0.1.0.dist-info/entry_points.txt
shape_registration-0.1.0.dist-info/top_level.txt
shape_registration-0.1.0.dist-info/RECORD
