Metadata-Version: 2.1
Name: shape-registration
Version: 0.1.0
Summary: This is a super duper package
Home-page: https://github.com/justusschock/shape-registration
Author: Justus Schock
Author-email: justus.schock@posteo.de
License: UNKNOWN
Project-URL: source, https://github.com/justusschock/shape-registration
Project-URL: tracker, https://github.com/justusschock/shape-registration/issues
Keywords: deep learning,machine learning,pytorch,medical,AI
Platform: UNKNOWN
Classifier: Programming Language :: Python :: 3
Requires-Python: >=3.7
Requires-Dist: torch (==1.9.0)
Requires-Dist: pytorch-lightning (==1.3.8)
Requires-Dist: numpy (==1.21.1)
Requires-Dist: torchmetrics (==0.4.1)
Requires-Dist: rising (==0.2.0post0)
Requires-Dist: scipy (==1.7.0)
Requires-Dist: scikit-image (==0.18.2)
Requires-Dist: SimpleITK (==2.0.2)
